otlmow_davie/AbstractRequester.py
otlmow_davie/CertRequester.py
otlmow_davie/CookieRequester.py
otlmow_davie/DavieClient.py
otlmow_davie/DavieDomain.py
otlmow_davie/DavieInternalRestClient.py
otlmow_davie/DavieRestClient.py
otlmow_davie/Enums.py
otlmow_davie/JWTRequester.py
otlmow_davie/RequesterFactory.py
otlmow_davie/__init__.py
otlmow_davie-0.4.dist-info/LICENSE
otlmow_davie-0.4.dist-info/METADATA
otlmow_davie-0.4.dist-info/WHEEL
otlmow_davie-0.4.dist-info/top_level.txt
otlmow_davie-0.4.dist-info/RECORD
