Metadata-Version: 2.1
Name: otlmow_davie
Version: 0.4
Author-email: David Vlaminck <david.vlaminck@mow.vlaanderen.be>
License:                     GNU GENERAL PUBLIC LICENSE
Project-URL: Homepage, https://github.com/davidvlaminck/OTLMOW-DAVIE
Project-URL: Bug Tracker, https://github.com/davidvlaminck/OTLMOW-DAVIE/issues
Classifier: Programming Language :: Python :: 3
Classifier: Programming Language :: Python :: 3.8
Classifier: Programming Language :: Python :: 3.9
Classifier: Programming Language :: Python :: 3.10
Classifier: Programming Language :: Python :: 3.11
Classifier: Programming Language :: Python :: 3.12
Classifier: Programming Language :: Python :: 3.13
Classifier: Operating System :: OS Independent
Requires-Python: >=3.7
License-File: LICENSE
